mendeley/__init__.py
mendeley/auth.py
mendeley/exception.py
mendeley/models.py
mendeley/pagination.py
mendeley/response.py
mendeley/session.py
mendeley/version.py
mendeley/models/__init__.py
mendeley/models/annotations.py
mendeley/models/base_documents.py
mendeley/models/catalog.py
mendeley/models/common.py
mendeley/models/documents.py
mendeley/models/files.py
mendeley/models/groups.py
mendeley/models/profiles.py
mendeley/resources/__init__.py
mendeley/resources/annotations.py
mendeley/resources/base.py
mendeley/resources/base_documents.py
mendeley/resources/catalog.py
mendeley/resources/documents.py
mendeley/resources/files.py
mendeley/resources/groups.py
mendeley/resources/profiles.py
mendeley/resources/trash.py
mendeley-0.3.2.dist-info/DESCRIPTION.rst
mendeley-0.3.2.dist-info/METADATA
mendeley-0.3.2.dist-info/metadata.json
mendeley-0.3.2.dist-info/pbr.json
mendeley-0.3.2.dist-info/RECORD
mendeley-0.3.2.dist-info/top_level.txt
mendeley-0.3.2.dist-info/WHEEL
