Metadata-Version: 1.1
Name: mendeley
Version: 0.3.2
Summary: Python SDK for the Mendeley API
Home-page: http://dev.mendeley.com
Author: Mendeley
Author-email: api@mendeley.com
License: Apache
Platform: UNKNOWN
Classifier: Development Status :: 4 - Beta
Classifier: Intended Audience :: Developers
Classifier: License :: OSI Approved :: Apache Software License
Classifier: Operating System :: OS Independent
Classifier: Programming Language :: Python
Classifier: Programming Language :: Python :: 2
Classifier: Programming Language :: Python :: 3
Classifier: Topic :: Scientific/Engineering
Classifier: Topic :: Software Development :: Libraries :: Python Modules
